Metadata-Version: 2.1
Name: mplppt
Version: 0.0.5
Summary: Convert a matplotlib figure to a powerpoint slide
Home-page: http://github.com/flaport/mplppt
Author: Floris Laporte
Author-email: floris.laporte@gmail.com
License: MIT
Platform: UNKNOWN
Classifier: Development Status :: 3 - Alpha
Classifier: Operating System :: OS Independent
Classifier: Programming Language :: Python :: 3
Classifier: Programming Language :: Python :: 2.7
Classifier: License :: OSI Approved :: MIT License
License-File: LICENSE
Requires-Dist: matplotlib
Requires-Dist: numpy
Requires-Dist: scipy
